natcap.versioner-0.5.0-py2.7-nspkg.pth
natcap/versioner/__init__.py
natcap/versioner/utils.py
natcap/versioner/version.py
natcap/versioner/versioning.py
natcap.versioner-0.5.0.dist-info/DESCRIPTION.rst
natcap.versioner-0.5.0.dist-info/METADATA
natcap.versioner-0.5.0.dist-info/RECORD
natcap.versioner-0.5.0.dist-info/WHEEL
natcap.versioner-0.5.0.dist-info/entry_points.txt
natcap.versioner-0.5.0.dist-info/metadata.json
natcap.versioner-0.5.0.dist-info/namespace_packages.txt
natcap.versioner-0.5.0.dist-info/top_level.txt
natcap.versioner-0.5.0.dist-info/zip-safe
