Metadata-Version: 2.0
Name: natcap.versioner
Version: 0.5.0
Summary: PEP440-compliant Git and hg versioning
Home-page: https://bitbucket.org/jdouglass/versioner
Author: James Douglass
Author-email: jdouglass@stanford.edu
License: BSD
Keywords: hg mercurial git versioning natcap
Platform: UNKNOWN
Classifier: Intended Audience :: Developers
Classifier: Development Status :: 4 - Beta
Classifier: Natural Language :: English
Classifier: Operating System :: MacOS :: MacOS X
Classifier: Operating System :: Microsoft
Classifier: Operating System :: POSIX
Classifier: Programming Language :: Python :: 2
Classifier: Programming Language :: Python :: 3
Classifier: Topic :: Software Development :: Version Control
Classifier: Topic :: Software Development :: Build Tools
Classifier: License :: OSI Approved :: BSD License
Requires-Dist: six
